Metadata-Version: 2.1
Name: gke-taskflow
Version: 1.0.0
Author-email: Recursion Pharmaceuticals <devs@recursionpharma.com>
Keywords: gke-taskflow
Classifier: Operating System :: OS Independent
Classifier: Programming Language :: Python
Classifier: Programming Language :: Python :: 3
Requires-Python: >=3.8
License-File: LICENSE
Requires-Dist: apache-airflow-providers-cncf-kubernetes
Requires-Dist: apache-airflow-providers-google
Provides-Extra: dev
Requires-Dist: bandit; extra == "dev"
Requires-Dist: black; extra == "dev"
Requires-Dist: itsdangerous; extra == "dev"
Requires-Dist: mypy; extra == "dev"
Requires-Dist: packaging; extra == "dev"
Requires-Dist: pre-commit; extra == "dev"
Requires-Dist: pytest; extra == "dev"
Requires-Dist: pyupgrade; extra == "dev"
Requires-Dist: radon; extra == "dev"
Requires-Dist: roadie; extra == "dev"
Requires-Dist: ruff; extra == "dev"
Requires-Dist: time-machine; extra == "dev"
Requires-Dist: types-click; extra == "dev"
Requires-Dist: types-pkg_resources; extra == "dev"
Requires-Dist: tox; extra == "dev"
Requires-Dist: validate-pyproject[all]; extra == "dev"
